{
  "basic_info": {
    "最新": 69.61,
    "股票代码": "002460",
    "股票简称": "赣锋锂业",
    "总股本": 2096694404.0,
    "流通股": 1211379763.0,
    "总市值": 145950897462.44,
    "流通市值": 84324145302.43,
    "行业": "能源金属",
    "上市时间": 20100810
  },
  "financial_indicators": {
    "流动比率": 1.37,
    "速动比率": 0.73,
    "产权比率": 0.68,
    "存货周转率": 3.38
  },
  "valuation": {
    "市盈率(TTM)": null,
    "市净率": null,
    "总市值": 145950897462.44
  },
  "performance_forecast": [],
  "dividend_info": [],
  "industry_analysis": {}
}